ga4bigquery/__init__.py
ga4bigquery/py.typed
ga4bigquery/core/__init__.py
ga4bigquery/core/client.py
ga4bigquery/core/helpers.py
ga4bigquery/core/request_events.py
ga4bigquery/core/request_funnel.py
ga4bigquery/core/types.py
ga4bigquery-1.0.0.dist-info/licenses/LICENSE
ga4bigquery-1.0.0.dist-info/METADATA
ga4bigquery-1.0.0.dist-info/WHEEL
ga4bigquery-1.0.0.dist-info/top_level.txt
ga4bigquery-1.0.0.dist-info/RECORD
