Metadata-Version: 2.4
Name: ga4bigquery
Version: 1.0.0
Summary: Lean GA4 BigQuery event + funnel querying
Author: Henrik Hortemo
License: MIT License
Project-URL: Homepage, https://github.com/hortemo/ga4bigquery
Project-URL: Repository, https://github.com/hortemo/ga4bigquery
Keywords: analytics,ga4,google-analytics,bigquery,funnel-analysis
Classifier: Development Status :: 5 - Production/Stable
Classifier: Intended Audience :: Developers
Classifier: License :: OSI Approved :: MIT License
Classifier: Programming Language :: Python :: 3
Classifier: Programming Language :: Python :: 3 :: Only
Classifier: Programming Language :: Python :: 3.12
Classifier: Topic :: Internet :: Log Analysis
Classifier: Topic :: Scientific/Engineering :: Information Analysis
Requires-Python: >=3.12
License-File: LICENSE
Requires-Dist: pandas>=1.5
Requires-Dist: google-cloud-bigquery>=3.13
Requires-Dist: google-cloud-bigquery-storage>=2.33
Requires-Dist: db-dtypes>=1.0.0
Provides-Extra: dev
Requires-Dist: pytest>=8; extra == "dev"
Requires-Dist: ruff>=0.4; extra == "dev"
Requires-Dist: build>=1.0; extra == "dev"
Requires-Dist: twine>=5.0; extra == "dev"
Dynamic: license-file
